MANIFEST.in
README.md
setup.py
django_graphql_accounts/__init__.py
django_graphql_accounts/admin.py
django_graphql_accounts/apps.py
django_graphql_accounts/models.py
django_graphql_accounts/mutations.py
django_graphql_accounts/queries.py
django_graphql_accounts/tasks.py
django_graphql_accounts/types.py
django_graphql_accounts/utils.py
django_graphql_accounts.egg-info/PKG-INFO
django_graphql_accounts.egg-info/SOURCES.txt
django_graphql_accounts.egg-info/dependency_links.txt
django_graphql_accounts.egg-info/requires.txt
django_graphql_accounts.egg-info/top_level.txt