Metadata-Version: 2.1
Name: django-graphql-accounts
Version: 0.12
Summary: A GraphQl API for user signup and authentication using email addresses
Home-page: https://github.com/mahdi-asadzadeh/django-graphql-accounts
Author: Mahdi Asadzadeh
Author-email: mahdi.asadzadeh.programing@gmail.com
License: UNKNOWN
Download-URL: https://github.com/mahdi-asadzadeh/django-graphql-accounts
Keywords: django,python,graphql,GraphQL,django-graphone,Graphone,api,auth,authentication,email,user,username,python-graphone,registration,signup,login,logout,password,django-registration,django-email-as-username
Platform: UNKNOWN
Classifier: Environment :: Web Environment
Classifier: Framework :: Django :: 2.2
Classifier: Framework :: Django :: 3.0
Classifier: Framework :: Django :: 3.1
Classifier: Framework :: Django :: 3.2
Classifier: Intended Audience :: Developers
Classifier: Natural Language :: English
Classifier: Operating System :: OS Independent
Classifier: Programming Language :: Python :: 3.6
Classifier: Programming Language :: Python :: 3.7
Classifier: Programming Language :: Python :: 3.8
Classifier: Topic :: Internet :: WWW/HTTP
Classifier: Topic :: Software Development
Classifier: Topic :: Utilities
